biobatchnet/__init__.py
biobatchnet/api.py
biobatchnet/imc.py
biobatchnet/parse_config.py
biobatchnet/run.sh
biobatchnet/scrna.py
biobatchnet/config/__init__.py
biobatchnet/config/IMC/Damond.yaml
biobatchnet/config/IMC/Hoch.yaml
biobatchnet/config/IMC/IMMUcan.yaml
biobatchnet/config/IMC/base_imc.yaml
biobatchnet/config/scRNA/base_rna.yaml
biobatchnet/config/scRNA/macaque.yaml
biobatchnet/config/scRNA/mousebrain.yaml
biobatchnet/config/scRNA/pancreas.yaml
biobatchnet/models/__init__.py
biobatchnet/models/model.py
biobatchnet/models/modules.py
biobatchnet/models/VampPrior/nn.py
biobatchnet/models/VampPrior/utils.py
biobatchnet/models/VampPrior/vampprior.py
biobatchnet/utils/__init__.py
biobatchnet/utils/dataset.py
biobatchnet/utils/evaluation.py
biobatchnet/utils/loss.py
biobatchnet/utils/trainer.py
biobatchnet/utils/user_dataset.py
biobatchnet/utils/util.py
biobatchnet-0.1.9.dist-info/licenses/LICENSE
biobatchnet-0.1.9.dist-info/METADATA
biobatchnet-0.1.9.dist-info/WHEEL
biobatchnet-0.1.9.dist-info/top_level.txt
biobatchnet-0.1.9.dist-info/RECORD
