Metadata-Version: 2.4
Name: biobatchnet
Version: 0.1.9
Summary: A VAE framework for batch effect correction in biological data
Author-email: Haiping Liu <haiping.liu.uom@gmail.com>
Maintainer-email: Haiping Liu <haiping.liu.uom@gmail.com>
License: MIT
Project-URL: Homepage, https://github.com/UoM-HealthAI/BioBatchNet
Project-URL: Repository, https://github.com/UoM-HealthAI/BioBatchNet
Keywords: batch-effect,deep-learning,single-cell,IMC,scRNA-seq,bioinformatics
Classifier: Development Status :: 3 - Alpha
Classifier: Intended Audience :: Science/Research
Classifier: Topic :: Scientific/Engineering :: Bio-Informatics
Classifier: Topic :: Scientific/Engineering :: Artificial Intelligence
Classifier: Programming Language :: Python :: 3.9
Classifier: Programming Language :: Python :: 3.10
Classifier: Programming Language :: Python :: 3.11
Classifier: Operating System :: OS Independent
Requires-Python: >=3.8
License-File: LICENSE
Requires-Dist: torch>=2.0.0
Requires-Dist: numpy>=1.24.0
Requires-Dist: pandas>=2.0.0
Requires-Dist: scikit-learn>=1.3.0
Requires-Dist: scipy>=1.10.0
Requires-Dist: tqdm>=4.65.0
Requires-Dist: pyyaml>=6.0
Requires-Dist: anndata>=0.9.0
Requires-Dist: scanpy>=1.9.0
Requires-Dist: matplotlib>=3.7.0
Requires-Dist: seaborn>=0.12.0
Requires-Dist: h5py>=3.8.0
Provides-Extra: full
Requires-Dist: scib>=1.0.0; extra == "full"
Dynamic: license-file
